Workbook
Name ib_beta: Drivers!$B$8
Name ib_cxpct: Drivers!$B$18
Name ib_dapct: Drivers!$B$17
Name ib_EBDA1: Forecast!$C$5
Name ib_EBDA2: Forecast!$D$5
Name ib_EBDA3: Forecast!$E$5
Name ib_EBDA4: Forecast!$F$5
Name ib_EBDA5: Forecast!$G$5
Name ib_ebmgn: Drivers!$B$16
Name ib_entrym: Drivers!$B$34
Name ib_erp: Drivers!$B$24
Name ib_exitm: Drivers!$B$31
Name ib_FCF1: Forecast!$C$13
Name ib_FCF2: Forecast!$D$13
Name ib_FCF3: Forecast!$E$13
Name ib_FCF4: Forecast!$F$13
Name ib_FCF5: Forecast!$G$13
Name ib_grw1: Drivers!$B$11
Name ib_grw2: Drivers!$B$12
Name ib_grw3: Drivers!$B$13
Name ib_grw4: Drivers!$B$14
Name ib_grw5: Drivers!$B$15
Name ib_hold: Drivers!$B$37
Name ib_kdLBO: Drivers!$B$36
Name ib_leverage: Drivers!$B$35
Name ib_netdebt: Drivers!$B$7
Name ib_nwcpct: Drivers!$B$19
Name ib_px: Drivers!$B$6
Name ib_rf: Drivers!$B$23
Name ib_shares: Drivers!$B$5
Name ib_spread: Drivers!$B$26
Name ib_sweep: Drivers!$B$38
Name ib_tax: Drivers!$B$20
Name ib_tg: Drivers!$B$30
Name ib_WACC: DCF!$B$13
Name ib_wd: Drivers!$B$27

Sheet Cover
A1: Micron Technology, Inc. (MU) — IB Valuation Template
A3: Sector | B3: Technology
A4: Industry | B4: Semiconductors
A5: Reporting Currency | B5: USD
A6: Fiscal Year End | B6: 2025-08-31
A7: As-of Date | B7: 2026-05-01
A8: Industry Preset | B8: semiconductors
A10: How to use this workbook
A11: 1. Yellow cells on the Drivers tab are editable — every other tab references them. 2. Edit any yellow cell to see the model recalculate live (DCF, LBO, M&A, Sensitivity all update). 3. Numbers in green are model OUTPUTS; do not overwrite. 4. Historicals are pulled from yfinance at the time the notebook ran; refresh by re-running it. 5. The Notes tab lists every place we used a fallback or historical average. 6. To value a different company, open the notebook, change the TICKER cell, and Run All.
A19: Headline outputs (linked to model)
A20: Current Market Price | B20: =Drivers!B6 -> 0
A21: DCF Implied Price | B21: =DCF!B40 -> 0
A22: DCF Upside / Downside | B22: =B21/B20-1 -> 0
A23: LBO Sponsor IRR | B23: =LBO!B40 -> 0
A24: LBO Sponsor MOIC | B24: =LBO!B41 -> 0

Sheet Drivers
A1: DRIVERS — every yellow cell is editable
A3: Company snapshot
A4: Ticker | B4: MU
A5: Shares Outstanding | B5: 1120000000
A6: Current Share Price | B6: 108.45
A7: Net Debt (latest) | B7: 3850000000
A8: Beta | B8: 1.27
A10: Operating drivers (Forecast tab uses these)
A11: Revenue Growth Y1 | B11: 0.2
A12: Revenue Growth Y2 | B12: 0.1
A13: Revenue Growth Y3 | B13: 0.05
A14: Revenue Growth Y4 | B14: 0.04
A15: Revenue Growth Y5 | B15: 0.03
A16: EBITDA Margin (mid-cycle) | B16: 0.32301885 | C16: 5y mid-cycle avg
A17: D&A % Revenue | B17: 0.15
A18: Capex % Revenue | B18: 0.22
A19: NWC % Δ Revenue | B19: 0.18
A20: Effective Tax Rate | B20: 0.15
A22: WACC inputs
A23: Risk-free rate | B23: 0.04
A24: Equity risk premium | B24: 0.055
A25: Beta (override) | B25: =B8 -> 0
A26: Credit spread (bps) | B26: 200
A27: Target Debt / EV | B27: 0.2
A29: Terminal value
A30: Terminal Growth (Gordon) | B30: 0.025
A31: Exit EBITDA Multiple | B31: 8
A33: LBO assumptions
A34: Entry EBITDA Multiple | B34: 8
A35: Debt / EBITDA at close | B35: 4.5
A36: Cost of LBO debt | B36: 0.085
A37: Hold period (yrs) | B37: 5
A38: Cash sweep % | B38: 0.75
A40: M&A assumptions
A41: Premium to current price | B41: 0.3
A42: Cost synergies (% target opex) | B42: 0.05
A43: Revenue synergies (% target rev) | B43: 0.02
A44: Synergy realization % | B44: 0.75
A45: Cost of new acquisition debt | B45: 0.07

Sheet Historicals
A1: Historical Financials (sourced: yfinance)
A2: Line Item ($ in reporting currency) | B2: 2021-08-31 | C2: 2022-08-31 | D2: 2023-08-31 | E2: 2024-08-31 | F2: 2025-08-31
A3: Revenue | B3: 27705000000 | C3: 30758000000 | D3: 15540000000 | E3: 25111000000 | F3: 35500000000
A4: YoY Growth % | C4: 0.11019672 | D4: -0.49476559 | E4: 0.61589447 | F4: 0.41372307
A5: Gross Profit | B5: 8533000000 | C5: 11740000000 | D5: -1416000000 | E5: 5611000000 | F5: 13500000000
A6: Gross Margin % | B6: 0.30799495 | C6: 0.38168932 | D6: -0.091119691 | E6: 0.22344789 | F6: 0.38028169
A7: EBITDA | B7: 13487000000 | C7: 13611000000 | D7: -1950000000 | E7: 8700000000 | F7: 16500000000
A8: EBITDA Margin % | B8: 0.48680744 | C8: 0.44251902 | D8: -0.12548263 | E8: 0.34646171 | F8: 0.46478873
A9: EBIT | B9: 6811000000 | C9: 8911000000 | D9: -5745000000 | E9: 811000000 | F9: 8300000000
A10: EBIT Margin % | B10: 0.2458401 | C10: 0.28971325 | D10: -0.36969112 | E10: 0.032296603 | F10: 0.23380282
A11: D&A | B11: 6676000000 | C11: 4700000000 | D11: 3795000000 | E11: 7889000000 | F11: 8200000000
A12: D&A % Revenue | B12: 0.24096733 | C12: 0.15280577 | D12: 0.24420849 | E12: 0.31416511 | F12: 0.23098592
A13: Net Income | B13: 5861000000 | C13: 8687000000 | D13: -5833000000 | E13: 778000000 | F13: 7220000000
A14: Net Margin % | B14: 0.21155026 | C14: 0.28243059 | D14: -0.37535393 | E14: 0.030982438 | F14: 0.20338028
A15: Diluted EPS | B15: 5.14 | C15: 7.79 | D15: -5.34 | E15: 0.7 | F15: 6.45
A16: Capex | B16: 9704000000 | C16: 12067000000 | D16: 7676000000 | E16: 8186000000 | F16: 10500000000
... A26: Total Equity | B26: 44137000000 | C26: 47180000000 | D26: 40544000000 | E26: 41200000000 | F26: 44300000000
A27: ROE % | C27: 0.1902603 | D27: -0.13298527 | E27: 0.019035036 | F27: 0.16888889
A28: ROIC % | C28: 0.18028201 | D28: -0.11716995 | E28: 0.017498813 | F28: 0.14827883
A29: Working Capital | B29: 5575000000 | C29: 7396000000 | D29: 7340000000 | E29: 7800000000 | F29: 7700000000
A30: NWC % Revenue | B30: 0.20122722 | C30: 0.24045777 | D30: 0.47232947 | E30: 0.31062084 | F30: 0.21690141

Sheet Forecast
A1: 5-Year Operating Forecast (formulas link to Drivers)
A2: Line Item | B2: FY2025 (Actual) | C2: FY2026E | D2: FY2027E | E2: FY2028E | F2: FY2029E | G2: FY2030E
A3: Revenue | B3: 35500000000 | C3: =B3*(1+ib_grw1) -> 0 | D3: =C3*(1+ib_grw2) -> 0 | E3: =D3*(1+ib_grw3) -> 0 | F3: =E3*(1+ib_grw4) -> 0 | G3: =F3*(1+ib_grw5) -> 0
A4: YoY Growth % | C4: =ib_grw1 -> 0 | D4: =ib_grw2 -> 0 | E4: =ib_grw3 -> 0 | F4: =ib_grw4 -> 0 | G4: =ib_grw5 -> 0
A5: EBITDA | C5: =C3*ib_ebmgn -> 0 | D5: =D3*ib_ebmgn -> 0 | E5: =E3*ib_ebmgn -> 0 | F5: =F3*ib_ebmgn -> 0 | G5: =G3*ib_ebmgn -> 0
A6: EBITDA Margin % | C6: =ib_ebmgn -> 0 | D6: =ib_ebmgn -> 0 | E6: =ib_ebmgn -> 0 | F6: =ib_ebmgn -> 0 | G6: =ib_ebmgn -> 0
A7: D&A | C7: =C3*ib_dapct -> 0 | D7: =D3*ib_dapct -> 0 | E7: =E3*ib_dapct -> 0 | F7: =F3*ib_dapct -> 0 | G7: =G3*ib_dapct -> 0
A8: EBIT | C8: =C5-C7 -> 0 | D8: =D5-D7 -> 0 | E8: =E5-E7 -> 0 | F8: =F5-F7 -> 0 | G8: =G5-G7 -> 0
A9: Cash Taxes | C9: =C8*ib_tax -> 0 | D9: =D8*ib_tax -> 0 | E9: =E8*ib_tax -> 0 | F9: =F8*ib_tax -> 0 | G9: =G8*ib_tax -> 0
A10: NOPAT | C10: =C8-C9 -> 0 | D10: =D8-D9 -> 0 | E10: =E8-E9 -> 0 | F10: =F8-F9 -> 0 | G10: =G8-G9 -> 0
A11: Capex | C11: =C3*ib_cxpct -> 0 | D11: =D3*ib_cxpct -> 0 | E11: =E3*ib_cxpct -> 0 | F11: =F3*ib_cxpct -> 0 | G11: =G3*ib_cxpct -> 0
A12: Δ Net Working Capital | C12: =(C3-B3)*ib_nwcpct -> 0 | D12: =(D3-C3)*ib_nwcpct -> 0 | E12: =(E3-D3)*ib_nwcpct -> 0 | F12: =(F3-E3)*ib_nwcpct -> 0 | G12: =(G3-F3)*ib_nwcpct -> 0
A13: Unlevered FCF | C13: =C10+C7-C11-C12 -> 0 | D13: =D10+D7-D11-D12 -> 0 | E13: =E10+E7-E11-E12 -> 0 | F13: =F10+F7-F11-F12 -> 0 | G13: =G10+G7-G11-G12 -> 0

Sheet DCF
A1: DCF Valuation (formulas only)
A3: WACC Build
A4: Risk-free rate | B4: =ib_rf -> 0
A5: Equity risk premium | B5: =ib_erp -> 0
A6: Beta | B6: =ib_beta -> 0
A7: Cost of Equity | B7: =B4+B5*B6 -> 0
A8: Pre-tax cost of debt | B8: =B4+ib_spread/10000 -> 0
A9: Tax rate | B9: =ib_tax -> 0
A10: After-tax cost of debt | B10: =B8*(1-B9) -> 0
A11: Weight of debt | B11: =ib_wd -> 0
A12: Weight of equity | B12: =1-B11 -> 0
A13: WACC | B13: =B7*B12+B10*B11 -> 0
A15: Year | B15: 1 | C15: 2 | D15: 3 | E15: 4 | F15: 5
A16: Unlevered FCF | B16: =Forecast!C13 -> 0 | C16: =Forecast!D13 -> 0 | D16: =Forecast!E13 -> 0 | E16: =Forecast!F13 -> 0 | F16: =Forecast!G13 -> 0
A17: Discount Factor | B17: =1/(1+ib_WACC)^1 -> 0 | C17: =1/(1+ib_WACC)^2 -> 0 | D17: =1/(1+ib_WACC)^3 -> 0 | E17: =1/(1+ib_WACC)^4 -> 0 | F17: =1/(1+ib_WACC)^5 -> 0
A18: PV of FCF | B18: =B16*B17 -> 0 | C18: =C16*C17 -> 0 | D18: =D16*D17 -> 0 | E18: =E16*E17 -> 0 | F18: =F16*F17 -> 0
A20: Sum of PV (explicit period) | B20: =SUM(B18:F18) -> 0
A21: Terminal FCF (Y5) | B21: =F16 -> 0
A22: Terminal Value — Gordon | B22: =B21*(1+ib_tg)/(ib_WACC-ib_tg) -> 0
A23: Terminal Value — Exit Mult | B23: =ib_EBDA5*ib_exitm -> 0
A24: Terminal Value — Blended | B24: =AVERAGE(B22,B23) -> 0
A25: PV of Terminal (blended) | B25: =B24*F17 -> 0
A26: Enterprise Value | B26: =B20+B25 -> 0
A27: Less: Net Debt | B27: =ib_netdebt -> 0
A28: Equity Value | B28: =B26-B27 -> 0
A29: Diluted Shares Out | B29: =ib_shares -> 0
A30: Implied Price | B30: =B28/B29 -> 0
A31: Current Price | B31: =ib_px -> 0
A32: Upside / (Downside) | B32: =B30/B31-1 -> 0
A34: Method comparison
A35: Method | B35: EV | C35: Equity | D35: Implied Px | E35: Upside %
A36: Gordon Growth | B36: =B20+B22*F17 -> 0 | C36: =B36-ib_netdebt -> 0 | D36: =C36/ib_shares -> 0 | E36: =D36/ib_px-1 -> 0
A37: Exit Multiple | B37: =B20+B23*F17 -> 0 | C37: =B37-ib_netdebt -> 0 | D37: =C37/ib_shares -> 0 | E37: =D37/ib_px-1 -> 0
A38: Blended (50/50) | B38: =B26 -> 0 | C38: =B28 -> 0 | D38: =B30 -> 0 | E38: =B32 -> 0
A40: Headline DCF Px | B40: =B30 -> 0

Sheet LBO
A1: LBO Model — Sources & Uses, Debt Schedule, Returns
A3: Sources
A4: Source | B4: $ Amount | C4: % of total
A5: New Term Debt | B5: =ib_EBDA1*ib_leverage -> 0 | C5: =B5/B7 -> 0
A6: Sponsor Equity | B6: =B12-B5+B11 -> 0 | C6: =B6/B7 -> 0
A7: Total Sources | B7: =B5+B6 -> 0 | C7: =1 -> 0
A9: Uses
A10: Use | B10: $ Amount
A11: Transaction Fees (2% of EV) | B11: =B12*0.02 -> 0
A12: Equity Purchase Price (incl. NetDebt assumption) | B12: =ib_EBDA1*ib_entrym -> 0
A13: Total Uses | B13: =B11+B12 -> 0
A15: Debt schedule
A16: Year | B16: Y1 | C16: Y2 | D16: Y3 | E16: Y4 | F16: Y5
A17: Beginning Debt | B17: =B5 -> 0 | C17: =B26 -> 0 | D17: =C26 -> 0 | E17: =D26 -> 0 | F17: =E26 -> 0
A18: Mandatory Amortization (1%) | B18: =B17*0.01 -> 0 | C18: =C17*0.01 -> 0 | D18: =D17*0.01 -> 0 | E18: =E17*0.01 -> 0 | F18: =F17*0.01 -> 0
A19: Cash Interest | B19: =B17*ib_kdLBO -> 0 | C19: =C17*ib_kdLBO -> 0 | D19: =D17*ib_kdLBO -> 0 | E19: =E17*ib_kdLBO -> 0 | F19: =F17*ib_kdLBO -> 0
A20: EBITDA | B20: =Forecast!C5 -> 0 | C20: =Forecast!D5 -> 0 | D20: =Forecast!E5 -> 0 | E20: =Forecast!F5 -> 0 | F20: =Forecast!G5 -> 0
A21: Less: Cash Taxes | B21: =(Forecast!C8-B19)*ib_tax -> 0 | C21: =(Forecast!D8-C19)*ib_tax -> 0 | D21: =(Forecast!E8-D19)*ib_tax -> 0 | E21: =(Forecast!F8-E19)*ib_tax -> 0 | F21: =(Forecast!G8-F19)*ib_tax -> 0
A22: Less: Capex | B22: =Forecast!C11 -> 0 | C22: =Forecast!D11 -> 0 | D22: =Forecast!E11 -> 0 | E22: =Forecast!F11 -> 0 | F22: =Forecast!G11 -> 0
A23: Less: Δ NWC | B23: =Forecast!C12 -> 0 | C23: =Forecast!D12 -> 0 | D23: =Forecast!E12 -> 0 | E23: =Forecast!F12 -> 0 | F23: =Forecast!G12 -> 0
A24: CFADS for Debt Paydown | B24: =B20-B19-MAX(0,B21)-B22-B23 -> 0 | C24: =C20-C19-MAX(0,C21)-C22-C23 -> 0 | D24: =D20-D19-MAX(0,D21)-D22-D23 -> 0 | E24: =E20-E19-MAX(0,E21)-E22-E23 -> 0 | F24: =F20-F19-MAX(0,F21)-F22-F23 -> 0
A25: Cash Sweep | B25: =MIN(MAX(0,(B24-B18))*ib_sweep,MAX(0,B17-B18)) -> 0 | C25: =MIN(MAX(0,(C24-C18))*ib_sweep,MAX(0,C17-C18)) -> 0 | D25: =MIN(MAX(0,(D24-D18))*ib_sweep,MAX(0,D17-D18)) -> 0 | E25: =MIN(MAX(0,(E24-E18))*ib_sweep,MAX(0,E17-E18)) -> 0 | F25: =MIN(MAX(0,(F24-F18))*ib_sweep,MAX(0,F17-F18)) -> 0
A26: Ending Debt | B26: =B17-B18-B25 -> 0 | C26: =C17-C18-C25 -> 0 | D26: =D17-D18-D25 -> 0 | E26: =E17-E18-E25 -> 0 | F26: =F17-F18-F25 -> 0
A27: Net Debt / EBITDA | B27: =B26/B20 -> 0 | C27: =C26/C20 -> 0 | D27: =D26/D20 -> 0 | E27: =E26/E20 -> 0 | F27: =F26/F20 -> 0
A28: Interest Coverage | B28: =B20/B19 -> 0 | C28: =C20/C19 -> 0 | D28: =D20/D19 -> 0 | E28: =E20/E19 -> 0 | F28: =F20/F19 -> 0
A30: Sponsor Returns
A31: Exit Year EBITDA | B31: =Forecast!G5 -> 0
A32: Exit Multiple | B32: =ib_exitm -> 0
A33: Exit Enterprise Value | B33: =B31*B32 -> 0
A34: Less: Exit Debt | B34: =F26 -> 0
A35: Plus: Cumulative Retained FCF | B35: =SUMPRODUCT((B24:F24-B25:F25-B18:F18>0)*(B24:F24-B25:F25-B18:F18)) -> 0
A36: Equity to Sponsor at Exit | B36: =B33-B34+B35 -> 0
A37: Sponsor Equity Invested | B37: =B6 -> 0
A38: MOIC | B38: =B36/B37 -> 0
A39: Hold Period | B39: =ib_hold -> 0
A40: IRR | B40: =B38^(1/B39)-1 -> 0
A41: MOIC (linked) | B41: =B38 -> 0

Sheet M&A
A1: M&A Accretion / Dilution
A3: Transaction summary
A4: Target Current Price | B4: 65
A5: Premium % | B5: 0.3
A6: Offer Price/Share | B6: 84.5
A7: Target Shares Outstanding | B7: 2.3076923e+08
A8: Equity Purchase Price | B8: 19500000000
A9: Target Net Debt Assumed | B9: 3050000000
A10: Deal Fees | B10: 338250000
A11: Total Deal Value | B11: 22550000000
A14: Pro-forma EPS by financing mix
A15: Metric | B15: All Stock | C15: All Cash | D15: 50/50 Mix
A16: Stock % | B16: 1 | C16: 0 | D16: 0.5
A17: Cash % | B17: 0 | C17: 1 | D17: 0.5
A18: New Shares Issued | B18: 1.7980636e+08 | C18: 0 | D18: 89903181
A19: New Debt Raised | B19: 338250000 | C19: 19838250000 | D19: 10088250000
A20: After-tax Interest | B20: 20125875 | C20: 1180375875 | D20: 6.0025088e+08
A21: Synergies (after-tax) | B21: 524343750 | C21: 524343750 | D21: 524343750
A22: Pro-forma Net Income | B22: 8124217875 | C22: 6963967875 | D22: 7544092875
A23: Pro-forma Shares | B23: 1.2998064e+09 | C23: 1120000000 | D23: 1.2099032e+09
A24: Pro-forma EPS | B24: 6.2503294 | C24: 6.2178285 | D24: 6.2352864
A25: Acquirer Standalone EPS | B25: 6.4464286 | C25: 6.4464286 | D25: 6.4464286
A26: Accretion / (Dilution) % | B26: -0.030419822 | C26: -0.035461513 | D26: -0.032753353

Sheet Comps
A1: Comparable Company Analysis
A3: Subject + Peer set
A4: Ticker | B4: Name | C4: Sector | D4: Industry | E4: Price | F4: Market Cap | G4: Enterprise Value | H4: Revenue | I4: EBITDA | J4: Net Income | K4: Diluted EPS | L4: Book Value | M4: EV/Revenue | N4: EV/EBITDA | O4: P/E | P4: P/B
A5: MU | B5: Micron Technology, Inc. | C5: Technology | D5: Semiconductors | E5: 108.45 | F5: 121500000000 | G5: 125350000000 | H5: 35500000000 | I5: 16500000000 | J5: 7220000000 | K5: 6.45 | L5: 44300000000 | M5: 3.5309859 | N5: 7.5969697 | O5: 16.813953 | P5: 2.7426637
A6: WDC | B6: Western Digital | C6: Technology | D6: Semiconductors | E6: 65 | F6: 15000000000 | G6: 19000000000 | H6: 12500000000 | I6: 1500000000 | J6: 400000000 | K6: 1.2 | L6: 5000000000 | M6: 1.52 | N6: 12.666667 | O6: 54.166667 | P6: 3
A7: STX | B7: Seagate Technology | C7: Technology | D7: Semiconductors | E7: 102 | F7: 22000000000 | G7: 27000000000 | H7: 7000000000 | I7: 1400000000 | J7: 600000000 | K7: 2.85 | L7: 1500000000 | M7: 3.8571429 | N7: 19.285714 | O7: 35.789474 | P7: 14.666667
A8: NVDA | B8: NVIDIA | C8: Technology | D8: Semiconductors | E8: 122 | F8: 3000000000000 | G8: 2980000000000 | H8: 130000000000 | I8: 80000000000 | J8: 60000000000 | K8: 2.45 | L8: 50000000000 | M8: 22.923077 | N8: 37.25 | O8: 49.795918 | P8: 60
A9: TSM | B9: Taiwan Semiconductor | C9: Technology | D9: Semiconductors | E9: 175 | F9: 900000000000 | G9: 870000000000 | H9: 90000000000 | I9: 60000000000 | J9: 33000000000 | K9: 6.3 | L9: 110000000000 | M9: 9.6666667 | N9: 14.5 | O9: 27.777778 | P9: 8.1818182
A10: AVGO | B10: Broadcom | C10: Technology | D10: Semiconductors | E10: 168 | F10: 790000000000 | G10: 850000000000 | H10: 50000000000 | I10: 30000000000 | J10: 14000000000 | K10: 3.1 | L10: 70000000000 | M10: 17 | N10: 28.333333 | O10: 54.193548 | P10: 11.285714
A11: INTC | B11: Intel | C11: Technology | D11: Semiconductors | E11: 23 | F11: 100000000000 | G11: 130000000000 | H11: 55000000000 | I11: 10000000000 | J11: 1000000000 | K11: 0.2 | L11: 110000000000 | M11: 2.3636364 | N11: 13 | O11: 115 | P11: 0.90909091
A12: AMD | B12: AMD | C12: Technology | D12: Semiconductors | E12: 137 | F12: 220000000000 | G12: 230000000000 | H12: 25000000000 | I12: 5000000000 | J12: 2000000000 | K12: 1.2 | L12: 55000000000 | M12: 9.2 | N12: 46 | O12: 114.16667 | P12: 4
A15: Peer-set statistics
A16: Multiple | B16: Min | C16: 25th %ile | D16: Median | E16: Mean | F16: 75th %ile | G16: Max
A17: EV/Revenue | B17: 1.52 | C17: 3.1103896 | D17: 9.2 | E17: 9.5043604 | F17: 13.333333 | G17: 22.923077
A18: EV/EBITDA | B18: 12.666667 | C18: 13.75 | D18: 19.285714 | E18: 24.433673 | F18: 32.791667 | G18: 46
A19: P/E | B19: 27.777778 | C19: 42.792696 | D19: 54.166667 | E19: 64.412865 | F19: 84.180108 | G19: 115
A20: P/B | B20: 0.90909091 | C20: 3.5 | D20: 8.1818182 | E20: 14.577613 | F20: 12.97619 | G20: 60
A23: Implied valuation (peer median × subject metric)
A24: Multiple | B24: Multiple Source | C24: Implied EV / Equity | D24: Implied Equity Value | E24: Implied Price/Share
A25: EV/Revenue | B25: Peer median × Revenue | C25: 326600000000 | D25: 322750000000 | E25: 288.16964
A26: EV/EBITDA | B26: Peer median × EBITDA | C26: 3.1821429e+11 | D26: 3.1436429e+11 | E26: 280.6824
A27: P/E | B27: Peer median × EPS | C27: 3.9515e+11 | D27: 3.913e+11 | E27: 349.375
A28: P/B | B28: Peer median × Book Value | C28: 3.6630455e+11 | D28: 3.6245455e+11 | E28: 323.62013

Sheet Sensitivity
A1: Sensitivity Tables
A3: DCF — Implied Price (WACC × Terminal Growth)
A4: WACC \ Terminal g | B4: 2.00% | C4: 2.25% | D4: 2.50% | E4: 2.75% | F4: 3.00%
A5: 8.81% | B5: 63.661542 | C5: 64.336669 | D5: 65.065309 | E5: 65.854088 | F5: 66.710771
A6: 9.31% | B6: 61.120855 | C6: 61.694617 | D6: 62.310517 | E6: 62.973375 | F6: 63.688775
A7: 9.81% | B7: 58.807088 | C7: 59.299509 | D7: 59.825621 | E7: 60.389004 | F7: 60.993763
A8: 10.31% | B8: 56.683149 | C8: 57.109402 | D8: 57.562952 | E8: 58.046505 | F8: 58.563143
A9: 10.81% | B9: 54.720213 | C9: 55.091993 | D9: 55.486147 | E9: 55.904759 | F9: 56.350177
A12: LBO — Sponsor IRR (Entry × Exit multiple)
A13: Entry × Exit | B13: 7.0x | C13: 7.5x | D13: 8.0x | E13: 8.5x | F13: 9.0x
A14: 7.0x | B14: 0.13169191 | C14: 0.16198479 | D14: 0.18941304 | E14: 0.21452236 | F14: 0.23771207
A15: 7.5x | B15: 0.088267459 | C15: 0.11739796 | D15: 0.14377376 | E15: 0.1679196 | F15: 0.19021949
A16: 8.0x | B16: 0.053245634 | C16: 0.08143868 | D16: 0.10696567 | E16: 0.13033447 | F16: 0.15191672
A17: 8.5x | B17: 0.024056254 | C17: 0.051467965 | D17: 0.076287509 | E17: 0.099008669 | F17: 0.11999279
A18: 9.0x | B18: -0.00086595506 | C18: 0.025878643 | D18: 0.050094161 | E18: 0.072262361 | F18: 0.092735799
A21: M&A — Y1 Accretion (Premium × Cost-Synergy)
A22: Premium \ Cost Synergy % | B22: 3.0% | C22: 4.0% | D22: 5.0% | E22: 6.0% | F22: 7.0%
A23: 20% | B23: -0.037440232 | C23: -0.028635139 | D23: -0.019830046 | E23: -0.011024953 | F23: -0.0022198606
A24: 25% | B24: -0.042669246 | C24: -0.033911251 | D24: -0.025153256 | E24: -0.016395261 | F24: -0.0076372667
A25: 30% | B25: -0.047842617 | C25: -0.039131219 | D25: -0.030419822 | E25: -0.021708424 | F25: -0.012997026
A26: 35% | B26: -0.05296123 | C26: -0.044295936 | D26: -0.035630642 | E26: -0.026965348 | F26: -0.018300054
A27: 40% | B27: -0.058025949 | C27: -0.049406273 | D27: -0.040786598 | E27: -0.032166922 | F27: -0.023547247

Sheet Football
A1: Football Field — Implied Equity Value Range
A3: Method | B3: Low | C3: Mid | D3: High | E3: Notes
A4: 52-week trading range | B4: 56.343612 | C4: 92.115251 | D4: 127.88689 | E4: From price history
A5: DCF (±5% WACC band) | B5: 50.851778 | C5: 59.825621 | D5: 68.799464 | E5: Driven by WACC ±50 bps
A6: Comps EV/EBITDA range | B6: 238.58004 | C6: 280.6824 | D6: 322.78476 | E6: Peer median × subject EBITDA, ±15%
A7: LBO entry @ target IRR | B7: 93.375522 | C7: 98.290023 | D7: 103.20452 | E7: Entry multiple from preset
A10: Current price (reference) | B10: =px -> 0

Sheet Notes
A1: Audit Trail — every fallback, derivation, or assumption
A2: Each line below was logged automatically when the data didn't exist or when an industry-preset assumption was used.
A4: [18:56:15] EBITDA margin set to 5y mid-cycle avg = 32.3%.
